{
  "persons": [
    {
      "name": "dsadsa",
      "number": "32523523",
      "id": 9
    },
    {
      "name": "",
      "number": "32523523",
      "id": 10
    },
    {
      "name": "4354W5R43543543543",
      "number": "32523523",
      "id": 11
    },
    {
      "name": "Arto Hellas",
      "number": "52152",
      "id": 12
    },
    {
      "name": "Pere Garcia Grau",
      "number": "sad",
      "id": 13
    },
    {
      "name": "Pedro garcia",
      "number": "654321",
      "id": 14
    }
  ]
}